{
  "1": {
    "title": "Mute",
    "author": "Maruthi Score Chesi",
    "genre": "Drama",
    "length": "5 pages",
    "pdf": "screenplays/short/Mute_ZerothDraft.pdf",
    "desc": "A misfit makes friends in a foreign land."
  },
  "2": {
    "title": "RESUME",
    "author": "Sai Krishna Meka",
    "genre": "Psychological Drama/Horror",
    "length": "6 pages",
    "pdf": "screenplays/short/RESUME_ZerothDraft.pdf",
    "desc": "Desperate to get a job a woman commits a deadly sin, or did she?"
  },
  "3": {
    "title": "Surprise!",
    "author": "Sai Krishna Meka",
    "genre": "Romance",
    "length": "3 pages",
    "pdf": "screenplays/short/Surprise_ ZerothDraft.pdf",
    "desc": "College love birds struggle to find the perfect gift for each other."
  }
}
